{
    "skills": [
        {
            "id": 1,
            "name": "HTML",
            "level": 95
        },
        {
            "id": 2,
            "name": "CSS",
            "level": 70
        },
        {
            "id": 3,
            "name": "TypeScript",
            "level": 85
        },
        {
            "id": 4,
            "name": "ReactJs",
            "level": 80
        },
        {
            "id": 5,
            "name": "Tailwind",
            "level": 70
        },
        {
            "id": 6,
            "name": "NodeJS",
            "level": 70
        },
        {
            "id": 7,
            "name": "docker",
            "level": 50
        }, 
        {
            "id": 8,
            "name": "AWS",
            "level": 40
        }
    ]
}